riigid/__init__.py
riigid/config.json
riigid/fragment.py
riigid/optimization_step.py
riigid/riigid.py
riigid/structure.py
riigid/convergence/__init__.py
riigid/convergence/criterion.py
riigid/convergence/displacement.py
riigid/convergence/force_torque.py
riigid/library/__init__.py
riigid/library/misc.py
riigid/library/rotation.py
riigid/optimizer/Deprecated_GDWAS.py
riigid/optimizer/GD.py
riigid/optimizer/GDWAS.py
riigid/optimizer/GPR.py
riigid/optimizer/__init__.py
riigid/optimizer/optimizer.py
RIIGID-1.1.3.dist-info/LICENSE.md
RIIGID-1.1.3.dist-info/METADATA
RIIGID-1.1.3.dist-info/WHEEL
RIIGID-1.1.3.dist-info/top_level.txt
RIIGID-1.1.3.dist-info/RECORD
