Metadata-Version: 2.1
Name: RIIGID
Version: 1.1.3
Summary: RIIGID - RIgid Interface Geometry IDentification
Home-page: https://github.com/siegfriedkaidisch/RIIGID
Author: Siegfried Kaidisch
Author-email: siegfried.kaidisch@uni-graz.at
License: MIT
Platform: UNKNOWN
Requires-Python: >3.9.0
License-File: LICENSE.md
Requires-Dist: ase
Requires-Dist: numpy
Requires-Dist: scikit-learn
Provides-Extra: dev
Requires-Dist: twine ; extra == 'dev'
Requires-Dist: wheel ; extra == 'dev'
